[
  {
    "slug": "what-is-examify",
    "title": "What is Examify? Features and Benefits Explained",
    "date": "2023-10-27",
    "author": "Examify Team",
    "excerpt": "Discover Examify, an online practice platform designed to help you excel in competitive exams with realistic simulations, custom tests, and detailed analysis.",
    "tags": ["Examify", "Features", "Introduction"],
    "mdFilePath": "/blogs/what-is-examify.md"
  },
  {
    "slug": "how-to-use-examify",
    "title": "How to Use Examify Effectively for Exam Prep",
    "date": "2023-10-26",
    "author": "Examify Team",
    "excerpt": "Learn the best ways to leverage Examify's features, from selecting tests and simulating exam conditions to analyzing your results for maximum improvement.",
    "tags": ["Examify", "Guide", "How-To", "Tips"],
    "mdFilePath": "/blogs/how-to-use-examify.md"
  },
  {
    "slug": "understanding-nimcet",
    "title": "Understanding the NIMCET Pattern: Tips & Strategies",
    "date": "2023-10-25",
    "excerpt": "A breakdown of the NIMCET exam structure, syllabus highlights, and effective strategies you can practice using Examify.",
    "tags": ["NIMCET", "Exam Prep", "Strategy", "Competitive Exams"],
    "mdFilePath": "/blogs/understanding-nimcet.md"
  }
]
